{
  "DEFECT": {
    "Runic Dome": {
      "boneName": "Neck_3",
      "large": false,
      "drawOrderSlotName": "Eye_up",
      "drawOrderZIndex": 0,
      "hideSlotNames": [],
      "requiredSlotNames": [],
      "exclusionGroup": "Head",
      "flipHorizontal": false,
      "flipVertical": false,
      "scaleX": 1.1512915,
      "scaleY": 1.1512915,
      "rotation": -43.651733,
      "position": {
        "x": 20.459612,
        "y": -2.9926753
      }
    },
    "CultistMask": {
      "boneName": "Neck_3",
      "large": false,
      "drawOrderSlotName": "Eye_up",
      "drawOrderZIndex": 0,
      "hideSlotNames": [
        "head",
        "Eye_up",
        "Eye_down"
      ],
      "requiredSlotNames": [],
      "exclusionGroup": "Head",
      "flipHorizontal": false,
      "flipVertical": false,
      "scaleX": 1.0,
      "scaleY": 1.0,
      "rotation": -15.0,
      "position": {
        "x": 8.107108,
        "y": -16.07093
      }
    },
    "Happy Flower": {
      "boneName": "Neck_3",
      "skeleton": {
        "name": "HappyFlower",
        "useRelicAsAtlas": true,
        "animations": [
          "headbob"
        ],
        "randomStartTime": true
      },
      "large": false,
      "drawOrderSlotName": "mantle",
      "drawOrderZIndex": 0,
      "hideSlotNames": [],
      "requiredSlotNames": [],
      "flipHorizontal": false,
      "flipVertical": false,
      "scaleX": 1.0,
      "scaleY": 1.0,
      "rotation": -21.972147,
      "position": {
        "x": 10.444821,
        "y": -6.9802785
      }
    },
    "Bag of Preparation": {
      "boneName": "Neck_2",
      "large": false,
      "drawOrderSlotName": "shadow",
      "drawOrderZIndex": 0,
      "hideSlotNames": [],
      "requiredSlotNames": [],
      "flipHorizontal": false,
      "flipVertical": false,
      "scaleX": 1.0702248,
      "scaleY": 1.0702248,
      "rotation": -101.897095,
      "position": {
        "x": 14.520237,
        "y": 15.992585
      }
    },
    "Regal Pillow": {
      "boneName": "Hips",
      "large": false,
      "drawOrderSlotName": "shadow",
      "drawOrderZIndex": 0,
      "hideSlotNames": [],
      "requiredSlotNames": [],
      "flipHorizontal": false,
      "flipVertical": false,
      "scaleX": 1.0,
      "scaleY": 1.0,
      "rotation": 0.65165365,
      "position": {
        "x": 1.0,
        "y": -23.900002
      }
    },
    "Juzu Bracelet": {
      "boneName": "Neck_",
      "large": false,
      "drawOrderSlotName": "mantle",
      "drawOrderZIndex": 0,
      "hideSlotNames": [],
      "requiredSlotNames": [],
      "flipHorizontal": false,
      "flipVertical": false,
      "scaleX": 0.6043866,
      "scaleY": 0.6043866,
      "rotation": -111.97884,
      "position": {
        "x": -6.39637,
        "y": -1.4165335
      }
    },
    "Potion Belt": {
      "boneName": "Hips",
      "large": false,
      "drawOrderSlotName": "left_quad",
      "drawOrderZIndex": 0,
      "hideSlotNames": [],
      "requiredSlotNames": [],
      "mask": "Potion Belt_P5Cy.png",
      "flipHorizontal": true,
      "flipVertical": false,
      "scaleX": 0.921875,
      "scaleY": 0.921875,
      "rotation": 7.934732,
      "position": {
        "x": 2.9000032,
        "y": -1.2999997
      }
    },
    "Dream Catcher": {
      "boneName": "Eye_down",
      "large": false,
      "drawOrderSlotName": "Eye_down",
      "drawOrderZIndex": 0,
      "hideSlotNames": [],
      "requiredSlotNames": [],
      "flipHorizontal": false,
      "flipVertical": false,
      "scaleX": 0.57096773,
      "scaleY": 0.57096773,
      "rotation": 0.0,
      "position": {
        "x": -1.6183778,
        "y": -25.998863
      }
    },
    "Bronze Scales": {
      "boneName": "Leg_R_2",
      "large": false,
      "drawOrderSlotName": "right_shin",
      "drawOrderZIndex": 0,
      "hideSlotNames": [],
      "requiredSlotNames": [],
      "flipHorizontal": false,
      "flipVertical": false,
      "scaleX": 0.5880779,
      "scaleY": 0.5880779,
      "rotation": -5.3236914,
      "position": {
        "x": 0.2429583,
        "y": 9.401647
      }
    },
    "DataDisk": {
      "boneName": "Leg_L_",
      "large": false,
      "drawOrderSlotName": "left_quad",
      "drawOrderZIndex": 0,
      "hideSlotNames": [],
      "requiredSlotNames": [],
      "flipHorizontal": false,
      "flipVertical": false,
      "scaleX": 0.5566502,
      "scaleY": 0.5566502,
      "rotation": 63.90572,
      "position": {
        "x": -7.0294557,
        "y": 5.0957584
      }
    },
    "Letter Opener": {
      "boneName": "bone3",
      "large": false,
      "drawOrderSlotName": "right_quad",
      "drawOrderZIndex": 0,
      "hideSlotNames": [],
      "requiredSlotNames": [],
      "flipHorizontal": false,
      "flipVertical": false,
      "scaleX": 0.7169811,
      "scaleY": 0.7169811,
      "rotation": -103.401924,
      "position": {
        "x": 4.7548637,
        "y": 19.35152
      }
    },
    "Eternal Feather": {
      "boneName": "Chest",
      "large": false,
      "drawOrderSlotName": "mantle",
      "drawOrderZIndex": 0,
      "hideSlotNames": [],
      "requiredSlotNames": [],
      "flipHorizontal": true,
      "flipVertical": true,
      "scaleX": 0.6429309,
      "scaleY": 0.6429309,
      "rotation": -18.293997,
      "position": {
        "x": -47.4,
        "y": 19.0
      }
    },
    "Cables": {
      "boneName": "Chest",
      "large": false,
      "drawOrderSlotName": "left_foot",
      "drawOrderZIndex": 0,
      "hideSlotNames": [],
      "requiredSlotNames": [],
      "flipHorizontal": false,
      "flipVertical": false,
      "scaleX": 0.7303166,
      "scaleY": 0.7303166,
      "rotation": -24.33591,
      "position": {
        "x": -19.099998,
        "y": -9.999999
      }
    },
    "Ornamental Fan": {
      "boneName": "bone6",
      "large": false,
      "drawOrderSlotName": "right_thumb",
      "drawOrderZIndex": 0,
      "hideSlotNames": [],
      "requiredSlotNames": [],
      "flipHorizontal": false,
      "flipVertical": false,
      "scaleX": 1.0,
      "scaleY": 1.0,
      "rotation": 161.16087,
      "position": {
        "x": 18.843164,
        "y": 3.6366467
      }
    },
    "Meat on the Bone": {
      "boneName": "bone7",
      "large": false,
      "drawOrderSlotName": "wire_main_neck",
      "drawOrderZIndex": 0,
      "hideSlotNames": [],
      "requiredSlotNames": [],
      "flipHorizontal": false,
      "flipVertical": false,
      "scaleX": 0.91121,
      "scaleY": 0.91121,
      "rotation": -55.10281,
      "position": {
        "x": -10.003959,
        "y": 26.909492
      }
    },
    "Runic Capacitor": {
      "boneName": "Hips",
      "large": false,
      "drawOrderSlotName": "left_shin",
      "drawOrderZIndex": 0,
      "hideSlotNames": [],
      "requiredSlotNames": [],
      "mask": "Runic Capacitor_u7Qu.png",
      "flipHorizontal": true,
      "flipVertical": false,
      "scaleX": 0.63083744,
      "scaleY": 0.63083744,
      "rotation": 70.70022,
      "position": {
        "x": -21.1,
        "y": -8.199999
      }
    },
    "FrozenCore": {
      "boneName": "Hips",
      "large": false,
      "drawOrderSlotName": "crackedOrb",
      "drawOrderZIndex": 0,
      "hideSlotNames": [
        "crackedOrb"
      ],
      "requiredSlotNames": [],
      "exclusionGroup": "Core",
      "mask": "FrozenCore_ESj0.png",
      "flipHorizontal": false,
      "flipVertical": false,
      "scaleX": 1.0,
      "scaleY": 1.0,
      "rotation": 0.0,
      "position": {
        "x": 1.4,
        "y": 0.90000004
      }
    },
    "Emotion Chip": {
      "boneName": "Neck_2",
      "large": false,
      "drawOrderSlotName": "wire_neck_l",
      "drawOrderZIndex": 0,
      "hideSlotNames": [],
      "requiredSlotNames": [],
      "flipHorizontal": true,
      "flipVertical": false,
      "scaleX": 0.39395335,
      "scaleY": 0.39395335,
      "rotation": -100.04703,
      "position": {
        "x": -14.724202,
        "y": 0.13373816
      }
    },
    "Snecko Eye": {
      "boneName": "Eye_down",
      "large": false,
      "drawOrderSlotName": "Eye_down",
      "drawOrderZIndex": 0,
      "hideSlotNames": [
        "Eye_down"
      ],
      "requiredSlotNames": [],
      "flipHorizontal": true,
      "flipVertical": true,
      "scaleX": 0.45260173,
      "scaleY": 0.45260173,
      "rotation": -317.45346,
      "position": {
        "x": -2.2008476,
        "y": -1.1984446
      }
    },
    "Velvet Choker": {
      "boneName": "Neck_2",
      "large": false,
      "drawOrderSlotName": "wire_neck_l",
      "drawOrderZIndex": 0,
      "hideSlotNames": [],
      "requiredSlotNames": [],
      "flipHorizontal": true,
      "flipVertical": false,
      "scaleX": 0.4449277,
      "scaleY": 0.4449277,
      "rotation": -77.39875,
      "position": {
        "x": 1.0242275,
        "y": -9.937854
      }
    },
    "WingedGreaves": {
      "boneName": "root",
      "large": false,
      "drawOrderSlotName": "left_foot",
      "drawOrderZIndex": 0,
      "hideSlotNames": [],
      "requiredSlotNames": [],
      "flipHorizontal": true,
      "flipVertical": false,
      "scaleX": 0.84435797,
      "scaleY": 0.84435797,
      "rotation": -13.717964,
      "position": {
        "x": -62.800003,
        "y": 14.499999
      }
    },
    "TungstenRod": {
      "boneName": "Arm_L_",
      "large": false,
      "drawOrderSlotName": "left_arm",
      "drawOrderZIndex": 0,
      "hideSlotNames": [
        "left_arm"
      ],
      "requiredSlotNames": [],
      "flipHorizontal": false,
      "flipVertical": false,
      "scaleX": 0.7236236,
      "scaleY": 0.7236236,
      "rotation": 162.3504,
      "position": {
        "x": -11.111048,
        "y": 7.4501467
      }
    },
    "The Courier": {
      "boneName": "Chest",
      "skeleton": {
        "name": "Courier",
        "useRelicAsAtlas": true,
        "animations": [
          "tail1",
          "tail2",
          "tail3",
          "ear_l",
          "ear_r",
          "blink"
        ],
        "randomStartTime": true
      },
      "large": false,
      "drawOrderSlotName": "head",
      "drawOrderZIndex": 0,
      "hideSlotNames": [],
      "requiredSlotNames": [],
      "flipHorizontal": true,
      "flipVertical": false,
      "scaleX": 0.5849448,
      "scaleY": 0.5849448,
      "rotation": 25.083267,
      "position": {
        "x": -37.422455,
        "y": -27.895409
      }
    },
    "Mummified Hand": {
      "boneName": "Arm_R_3",
      "large": false,
      "drawOrderSlotName": "right_hand",
      "drawOrderZIndex": 0,
      "hideSlotNames": [
        "right_thumb",
        "right_finger_1",
        "right_hand",
        "right_finger_2"
      ],
      "requiredSlotNames": [],
      "mask": "Mummified Hand_e9T3.png",
      "flipHorizontal": false,
      "flipVertical": false,
      "scaleX": 0.4982049,
      "scaleY": 0.4982049,
      "rotation": -42.029823,
      "position": {
        "x": 6.574832,
        "y": 9.234262
      }
    },
    "CaptainsWheel": {
      "boneName": "Neck_3",
      "large": false,
      "drawOrderSlotName": "mantle",
      "drawOrderZIndex": 0,
      "hideSlotNames": [],
      "requiredSlotNames": [
        "head"
      ],
      "mask": "CaptainsWheel_N3es.png",
      "flipHorizontal": false,
      "flipVertical": false,
      "scaleX": 1.0,
      "scaleY": 1.0,
      "rotation": -170.76938,
      "position": {
        "x": 25.259666,
        "y": 1.6701162
      }
    },
    "Omamori": {
      "boneName": "Chest",
      "large": false,
      "drawOrderSlotName": "mantle",
      "drawOrderZIndex": 0,
      "hideSlotNames": [],
      "requiredSlotNames": [],
      "mask": "Omamori_X5Yj.png",
      "flipHorizontal": true,
      "flipVertical": false,
      "scaleX": 0.5404531,
      "scaleY": 0.5404531,
      "rotation": 0.0,
      "position": {
        "x": 6.2000027,
        "y": -5.700002
      }
    },
    "Darkstone Periapt": {
      "boneName": "Chest",
      "large": false,
      "drawOrderSlotName": "mantle",
      "drawOrderZIndex": 1,
      "hideSlotNames": [],
      "requiredSlotNames": [],
      "mask": "Darkstone Periapt_9Aau.png",
      "flipHorizontal": true,
      "flipVertical": false,
      "scaleX": 0.52073026,
      "scaleY": 0.52073026,
      "rotation": -33.453827,
      "position": {
        "x": 0.49999985,
        "y": -5.3999996
      }
    },
    "Calipers": {
      "boneName": "Arm_L_3",
      "large": false,
      "drawOrderSlotName": "left_forearm",
      "drawOrderZIndex": 0,
      "hideSlotNames": [
        "left_thumb",
        "left_finger_2",
        "left_finger_1",
        "left_finger_3"
      ],
      "requiredSlotNames": [],
      "mask": "Calipers_KBaR.png",
      "flipHorizontal": false,
      "flipVertical": false,
      "scaleX": 0.93061227,
      "scaleY": 0.93061227,
      "rotation": 153.54482,
      "position": {
        "x": -9.310123,
        "y": 8.181785
      }
    },
    "Dead Branch": {
      "boneName": "Leg_R_2",
      "large": false,
      "drawOrderSlotName": "right_shin",
      "drawOrderZIndex": -1,
      "hideSlotNames": [
        "right_shin"
      ],
      "requiredSlotNames": [],
      "flipHorizontal": true,
      "flipVertical": false,
      "scaleX": 1.0,
      "scaleY": 1.0,
      "rotation": -136.72652,
      "position": {
        "x": 11.526812,
        "y": 11.528772
      }
    },
    "Nuclear Battery": {
      "boneName": "Hips",
      "large": false,
      "drawOrderSlotName": "crackedOrb",
      "drawOrderZIndex": 0,
      "hideSlotNames": [
        "crackedOrb"
      ],
      "requiredSlotNames": [],
      "exclusionGroup": "Core",
      "mask": "Nuclear Battery_ekI5.png",
      "flipHorizontal": false,
      "flipVertical": false,
      "scaleX": 1.0,
      "scaleY": 1.0,
      "rotation": 0.0,
      "position": {
        "x": 0.0,
        "y": 0.0
      }
    },
    "Strange Spoon": {
      "boneName": "root",
      "skeleton": {
        "name": "Orbit",
        "useRelicAsAtlas": true,
        "animations": [
          "orbit",
          "rotate"
        ],
        "randomStartTime": true,
        "boneTransforms": [
          {
            "name": "relic",
            "rotation": -38.0,
            "scaleX": 0.68,
            "scaleY": 0.68
          }
        ]
      },
      "large": false,
      "drawOrderSlotName": "left_thumb",
      "drawOrderZIndex": 0,
      "hideSlotNames": [],
      "requiredSlotNames": [],
      "flipHorizontal": false,
      "flipVertical": false,
      "scaleX": 1.0,
      "scaleY": 1.0,
      "rotation": 0.0,
      "position": {
        "x": 3.6729193,
        "y": -98.079346
      }
    },
    "Anchor": {
      "boneName": "root",
      "skeleton": {
        "name": "Orbit",
        "useRelicAsAtlas": true,
        "animations": [
          "orbit",
          "rotate"
        ],
        "randomStartTime": true,
        "boneTransforms": [
          {
            "name": "relic",
            "rotation": 30.0
          }
        ]
      },
      "large": false,
      "drawOrderSlotName": "left_thumb",
      "drawOrderZIndex": 0,
      "hideSlotNames": [],
      "requiredSlotNames": [],
      "flipHorizontal": false,
      "flipVertical": false,
      "scaleX": 1.0,
      "scaleY": 1.0,
      "rotation": 0.0,
      "position": {
        "x": 3.6729193,
        "y": -98.079346
      }
    },
    "HornCleat": {
      "boneName": "root",
      "skeleton": {
        "name": "Orbit",
        "useRelicAsAtlas": true,
        "animations": [
          "orbit",
          "rotate"
        ],
        "randomStartTime": true,
        "boneTransforms": [
          {
            "name": "relic",
            "rotation": -91.0,
            "scaleX": 0.9,
            "scaleY": 0.9
          }
        ]
      },
      "large": false,
      "drawOrderSlotName": "left_thumb",
      "drawOrderZIndex": 0,
      "hideSlotNames": [],
      "requiredSlotNames": [],
      "flipHorizontal": false,
      "flipVertical": false,
      "scaleX": 1.0,
      "scaleY": 1.0,
      "rotation": 0.0,
      "position": {
        "x": 3.6729193,
        "y": -98.079346
      }
    },
    "Mercury Hourglass": {
      "boneName": "root",
      "skeleton": {
        "name": "Orbit",
        "useRelicAsAtlas": true,
        "animations": [
          "orbit",
          "rotate"
        ],
        "randomStartTime": true,
        "boneTransforms": [
          {
            "name": "relic",
            "rotation": 10.0,
            "scaleX": 0.65,
            "scaleY": 0.65
          }
        ]
      },
      "large": false,
      "drawOrderSlotName": "left_thumb",
      "drawOrderZIndex": 0,
      "hideSlotNames": [],
      "requiredSlotNames": [],
      "flipHorizontal": false,
      "flipVertical": false,
      "scaleX": 1.0,
      "scaleY": 1.0,
      "rotation": 0.0,
      "position": {
        "x": 3.6729193,
        "y": -98.079346
      }
    },
    "Kunai": {
      "boneName": "root",
      "skeleton": {
        "name": "Orbit",
        "useRelicAsAtlas": true,
        "animations": [
          "orbit",
          "rotate"
        ],
        "randomStartTime": true,
        "boneTransforms": [
          {
            "name": "relic",
            "rotation": 37.0,
            "scaleX": -1.0
          }
        ]
      },
      "large": false,
      "drawOrderSlotName": "left_thumb",
      "drawOrderZIndex": 0,
      "hideSlotNames": [],
      "requiredSlotNames": [],
      "flipHorizontal": false,
      "flipVertical": false,
      "scaleX": 1.0,
      "scaleY": 1.0,
      "rotation": 0.0,
      "position": {
        "x": 3.6729193,
        "y": -98.079346
      }
    },
    "Shuriken": {
      "boneName": "root",
      "skeleton": {
        "name": "Orbit",
        "useRelicAsAtlas": true,
        "animations": [
          "orbit",
          "spin"
        ],
        "randomStartTime": true,
        "boneTransforms": [
          {
            "name": "relic",
            "scaleX": 0.585,
            "scaleY": 0.585
          }
        ]
      },
      "large": false,
      "drawOrderSlotName": "left_thumb",
      "drawOrderZIndex": 0,
      "hideSlotNames": [],
      "requiredSlotNames": [],
      "flipHorizontal": false,
      "flipVertical": false,
      "scaleX": 1.0,
      "scaleY": 1.0,
      "rotation": 0.0,
      "position": {
        "x": 3.6729193,
        "y": -98.079346
      }
    },
    "ClockworkSouvenir": {
      "boneName": "root",
      "skeleton": {
        "name": "Orbit",
        "useRelicAsAtlas": true,
        "animations": [
          "orbit",
          "tickTock"
        ],
        "randomStartTime": true,
        "boneTransforms": [
          {
            "name": "relic",
            "scaleX": 0.6,
            "scaleY": 0.6
          }
        ]
      },
      "large": false,
      "drawOrderSlotName": "left_thumb",
      "drawOrderZIndex": 0,
      "hideSlotNames": [],
      "requiredSlotNames": [],
      "flipHorizontal": false,
      "flipVertical": false,
      "scaleX": 1.0,
      "scaleY": 1.0,
      "rotation": 0.0,
      "position": {
        "x": 3.6729193,
        "y": -98.079346
      }
    },
    "Frozen Eye": {
      "boneName": "Eye_up",
      "large": false,
      "drawOrderSlotName": "Eye_up",
      "drawOrderZIndex": 0,
      "hideSlotNames": [
        "Eye_up"
      ],
      "requiredSlotNames": [],
      "flipHorizontal": false,
      "flipVertical": false,
      "scaleX": 0.33603677,
      "scaleY": 0.33603677,
      "rotation": -42.309425,
      "position": {
        "x": 0.0,
        "y": 0.0
      }
    },
    "Lantern": {
      "boneName": "root",
      "skeleton": {
        "name": "Orbit",
        "useRelicAsAtlas": true,
        "animations": [
          "orbit",
          "rotate"
        ],
        "randomStartTime": true,
        "boneTransforms": [
          {
            "name": "relic",
            "scaleX": -0.7,
            "scaleY": 0.7
          }
        ]
      },
      "large": false,
      "drawOrderSlotName": "left_thumb",
      "drawOrderZIndex": 0,
      "hideSlotNames": [],
      "requiredSlotNames": [],
      "flipHorizontal": false,
      "flipVertical": false,
      "scaleX": 1.0,
      "scaleY": 1.0,
      "rotation": 0.0,
      "position": {
        "x": 3.6729193,
        "y": -98.079346
      }
    },
    "Astrolabe": {
      "boneName": "root",
      "skeleton": {
        "name": "Orbit",
        "useRelicAsAtlas": true,
        "animations": [
          "orbit",
          "rotate"
        ],
        "randomStartTime": true,
        "boneTransforms": [
          {
            "name": "relic",
            "scaleX": 0.78,
            "scaleY": 0.78
          }
        ]
      },
      "large": false,
      "drawOrderSlotName": "left_thumb",
      "drawOrderZIndex": 0,
      "hideSlotNames": [],
      "requiredSlotNames": [],
      "flipHorizontal": false,
      "flipVertical": false,
      "scaleX": 1.0,
      "scaleY": 1.0,
      "rotation": 0.0,
      "position": {
        "x": 3.6729193,
        "y": -98.079346
      }
    }
  }
}